gym_modelspin/__init__.py
gym_modelspin/envs/__init__.py
gym_modelspin/envs/modelspin.py
gym_modelspin/wrappers/__init__.py
gym_modelspin-0.0.3.dist-info/METADATA
gym_modelspin-0.0.3.dist-info/WHEEL
gym_modelspin-0.0.3.dist-info/top_level.txt
gym_modelspin-0.0.3.dist-info/RECORD
