Metadata-Version: 2.1
Name: gym-modelspin
Version: 0.0.3
Requires-Dist: gym (==0.26.0)
